MANIFEST.in
readme.md
setup.py
ukbc/GUI.py
ukbc/UKBcrunch.py
ukbc/__init__.py
ukbc.egg-info/PKG-INFO
ukbc.egg-info/SOURCES.txt
ukbc.egg-info/dependency_links.txt
ukbc.egg-info/not-zip-safe
ukbc.egg-info/requires.txt
ukbc.egg-info/top_level.txt
ukbc/coding_files/__init__.py
ukbc/coding_files/coding3.tsv
ukbc/coding_files/coding4.tsv
ukbc/coding_files/coding6.tsv
ukbc/data/sample_data.csv
ukbc/data/sample_data.html
ukbc/gui_functions/__init__.py
ukbc/gui_functions/gui_functions.py
ukbc/images/__init__.py
ukbc/images/ukb_logo.gif
ukbc/ukbc_functions/Filtering.py
ukbc/ukbc_functions/__init__.py