Metadata-Version: 1.0
Name: ukbc
Version: 1.2
Summary: Interface to faciliate filtering of UKBioBank data
Home-page: http://github.com/jnecus/ukbcrunch
Author: Joe Necus
Author-email: j.necus2@ncl.ac.uk
License: MIT
Platform: UNKNOWN
